dotted_name_resolver/__init__.py
dotted_name_resolver/tests/__init__.py
dotted_name_resolver/tests/test_dotted_name_resolver.py
dotted_name_resolver-0.2.3.dist-info/METADATA
dotted_name_resolver-0.2.3.dist-info/WHEEL
dotted_name_resolver-0.2.3.dist-info/top_level.txt
dotted_name_resolver-0.2.3.dist-info/RECORD
